lppl/__init__.py
lppl/fit.py
lppl/numerics.py
lppl-0.0.4.dist-info/LICENSE
lppl-0.0.4.dist-info/METADATA
lppl-0.0.4.dist-info/WHEEL
lppl-0.0.4.dist-info/top_level.txt
lppl-0.0.4.dist-info/RECORD
